aiden_gsuite/__init__.py
aiden_gsuite/calendar.py
aiden_gsuite/credential.py
aiden_gsuite/drive.py
aiden_gsuite/gmail.py
aiden_gsuite/server.py
aiden_gsuite/toolhandler.py
aiden_gsuite/tools_calendar.py
aiden_gsuite/tools_drive.py
aiden_gsuite/tools_gmail.py
aiden_gsuite/tools_map.py
aiden_gsuite-0.4.1.dist-info/METADATA
aiden_gsuite-0.4.1.dist-info/WHEEL
aiden_gsuite-0.4.1.dist-info/entry_points.txt
aiden_gsuite-0.4.1.dist-info/licenses/LICENSE
aiden_gsuite-0.4.1.dist-info/RECORD
